{
  "openapi": "3.0.1",
  "info": {
    "title": "Travel.API",
    "version": "1.0"
  },
  "paths": {
    "/Auth/GetToken": {
      "post": {
        "tags": [
          "Auth"
        ],
        "requestBody": {
          "content": {
            "application/json": {
              "schema": {
                "$ref": "#/components/schemas/LoginDto"
              }
            },
            "text/json": {
              "schema": {
                "$ref": "#/components/schemas/LoginDto"
              }
            },
            "application/*+json": {
              "schema": {
                "$ref": "#/components/schemas/LoginDto"
              }
            }
          }
        },
        "responses": {
          "400": {
            "description": "Bad Request",
            "content": {
              "text/plain": {
                "schema": {
                  "$ref": "#/components/schemas/JsonResponse"
                }
              },
              "application/json": {
                "schema": {
                  "$ref": "#/components/schemas/JsonResponse"
                }
              },
              "text/json": {
                "schema": {
                  "$ref": "#/components/schemas/JsonResponse"
                }
              }
            }
          },
          "401": {
            "description": "Unauthorized",
            "content": {
              "text/plain": {
                "schema": {
                  "$ref": "#/components/schemas/JsonResponse"
                }
              },
              "application/json": {
                "schema": {
                  "$ref": "#/components/schemas/JsonResponse"
                }
              },
              "text/json": {
                "schema": {
                  "$ref": "#/components/schemas/JsonResponse"
                }
              }
            }
          },
          "500": {
            "description": "Internal Server Error",
            "content": {
              "text/plain": {
                "schema": {
                  "$ref": "#/components/schemas/JsonResponse"
                }
              },
              "application/json": {
                "schema": {
                  "$ref": "#/components/schemas/JsonResponse"
                }
              },
              "text/json": {
                "schema": {
                  "$ref": "#/components/schemas/JsonResponse"
                }
              }
            }
          },
          "default": {
            "description": "Unexpected error",
            "content": {
              "application/json": {
                "schema": {
                  "$ref": "#/components/schemas/JsonResponse"
                }
              }
            }
          }
        }
      }
    },
    "/Auth/SendOTP": {
      "post": {
        "tags": [
          "Auth"
        ],
        "requestBody": {
          "content": {
            "application/json": {
              "schema": {
                "$ref": "#/components/schemas/LoginViaOtpModel"
              }
            },
            "text/json": {
              "schema": {
                "$ref": "#/components/schemas/LoginViaOtpModel"
              }
            },
            "application/*+json": {
              "schema": {
                "$ref": "#/components/schemas/LoginViaOtpModel"
              }
            }
          }
        },
        "responses": {
          "400": {
            "description": "Bad Request",
            "content": {
              "text/plain": {
                "schema": {
                  "$ref": "#/components/schemas/JsonResponse"
                }
              },
              "application/json": {
                "schema": {
                  "$ref": "#/components/schemas/JsonResponse"
                }
              },
              "text/json": {
                "schema": {
                  "$ref": "#/components/schemas/JsonResponse"
                }
              }
            }
          },
          "401": {
            "description": "Unauthorized",
            "content": {
              "text/plain": {
                "schema": {
                  "$ref": "#/components/schemas/JsonResponse"
                }
              },
              "application/json": {
                "schema": {
                  "$ref": "#/components/schemas/JsonResponse"
                }
              },
              "text/json": {
                "schema": {
                  "$ref": "#/components/schemas/JsonResponse"
                }
              }
            }
          },
          "500": {
            "description": "Internal Server Error",
            "content": {
              "text/plain": {
                "schema": {
                  "$ref": "#/components/schemas/JsonResponse"
                }
              },
              "application/json": {
                "schema": {
                  "$ref": "#/components/schemas/JsonResponse"
                }
              },
              "text/json": {
                "schema": {
                  "$ref": "#/components/schemas/JsonResponse"
                }
              }
            }
          },
          "default": {
            "description": "Unexpected error",
            "content": {
              "application/json": {
                "schema": {
                  "$ref": "#/components/schemas/JsonResponse"
                }
              }
            }
          }
        }
      }
    },
    "/Auth/GetProfile": {
      "post": {
        "tags": [
          "Auth"
        ],
        "requestBody": {
          "content": {
            "application/json": {
              "schema": {
                "$ref": "#/components/schemas/GetByUsrno"
              }
            },
            "text/json": {
              "schema": {
                "$ref": "#/components/schemas/GetByUsrno"
              }
            },
            "application/*+json": {
              "schema": {
                "$ref": "#/components/schemas/GetByUsrno"
              }
            }
          }
        },
        "responses": {
          "400": {
            "description": "Bad Request",
            "content": {
              "text/plain": {
                "schema": {
                  "$ref": "#/components/schemas/JsonResponse"
                }
              },
              "application/json": {
                "schema": {
                  "$ref": "#/components/schemas/JsonResponse"
                }
              },
              "text/json": {
                "schema": {
                  "$ref": "#/components/schemas/JsonResponse"
                }
              }
            }
          },
          "401": {
            "description": "Unauthorized",
            "content": {
              "text/plain": {
                "schema": {
                  "$ref": "#/components/schemas/JsonResponse"
                }
              },
              "application/json": {
                "schema": {
                  "$ref": "#/components/schemas/JsonResponse"
                }
              },
              "text/json": {
                "schema": {
                  "$ref": "#/components/schemas/JsonResponse"
                }
              }
            }
          },
          "500": {
            "description": "Internal Server Error",
            "content": {
              "text/plain": {
                "schema": {
                  "$ref": "#/components/schemas/JsonResponse"
                }
              },
              "application/json": {
                "schema": {
                  "$ref": "#/components/schemas/JsonResponse"
                }
              },
              "text/json": {
                "schema": {
                  "$ref": "#/components/schemas/JsonResponse"
                }
              }
            }
          },
          "default": {
            "description": "Unexpected error",
            "content": {
              "application/json": {
                "schema": {
                  "$ref": "#/components/schemas/JsonResponse"
                }
              }
            }
          }
        }
      }
    },
    "/Flight/Airports": {
      "post": {
        "tags": [
          "Flight"
        ],
        "requestBody": {
          "content": {
            "application/json": {
              "schema": {
                "$ref": "#/components/schemas/SearchAirport"
              }
            },
            "text/json": {
              "schema": {
                "$ref": "#/components/schemas/SearchAirport"
              }
            },
            "application/*+json": {
              "schema": {
                "$ref": "#/components/schemas/SearchAirport"
              }
            }
          }
        },
        "responses": {
          "200": {
            "description": "OK",
            "content": {
              "text/plain": {
                "schema": {
                  "$ref": "#/components/schemas/CityAirportListListJsonResponse"
                }
              },
              "application/json": {
                "schema": {
                  "$ref": "#/components/schemas/CityAirportListListJsonResponse"
                }
              },
              "text/json": {
                "schema": {
                  "$ref": "#/components/schemas/CityAirportListListJsonResponse"
                }
              }
            }
          },
          "default": {
            "description": "Unexpected error",
            "content": {
              "application/json": {
                "schema": {
                  "$ref": "#/components/schemas/JsonResponse"
                }
              }
            }
          }
        }
      }
    },
    "/Flight/Search": {
      "post": {
        "tags": [
          "Flight"
        ],
        "requestBody": {
          "content": {
            "application/json": {
              "schema": {
                "$ref": "#/components/schemas/SearchRequestDto"
              }
            },
            "text/json": {
              "schema": {
                "$ref": "#/components/schemas/SearchRequestDto"
              }
            },
            "application/*+json": {
              "schema": {
                "$ref": "#/components/schemas/SearchRequestDto"
              }
            }
          }
        },
        "responses": {
          "200": {
            "description": "OK",
            "content": {
              "text/plain": {
                "schema": {
                  "$ref": "#/components/schemas/FlightResultsJsonResponse"
                }
              },
              "application/json": {
                "schema": {
                  "$ref": "#/components/schemas/FlightResultsJsonResponse"
                }
              },
              "text/json": {
                "schema": {
                  "$ref": "#/components/schemas/FlightResultsJsonResponse"
                }
              }
            }
          },
          "default": {
            "description": "Unexpected error",
            "content": {
              "application/json": {
                "schema": {
                  "$ref": "#/components/schemas/JsonResponse"
                }
              }
            }
          }
        }
      }
    },
    "/Flight/FlightDetails": {
      "post": {
        "tags": [
          "Flight"
        ],
        "requestBody": {
          "content": {
            "application/json": {
              "schema": {
                "$ref": "#/components/schemas/FlightDetailsRequestDto"
              }
            },
            "text/json": {
              "schema": {
                "$ref": "#/components/schemas/FlightDetailsRequestDto"
              }
            },
            "application/*+json": {
              "schema": {
                "$ref": "#/components/schemas/FlightDetailsRequestDto"
              }
            }
          }
        },
        "responses": {
          "200": {
            "description": "OK",
            "content": {
              "text/plain": {
                "schema": {
                  "$ref": "#/components/schemas/FlightDetailModelJsonResponse"
                }
              },
              "application/json": {
                "schema": {
                  "$ref": "#/components/schemas/FlightDetailModelJsonResponse"
                }
              },
              "text/json": {
                "schema": {
                  "$ref": "#/components/schemas/FlightDetailModelJsonResponse"
                }
              }
            }
          },
          "default": {
            "description": "Unexpected error",
            "content": {
              "application/json": {
                "schema": {
                  "$ref": "#/components/schemas/JsonResponse"
                }
              }
            }
          }
        }
      }
    },
    "/Flight/Seats": {
      "post": {
        "tags": [
          "Flight"
        ],
        "requestBody": {
          "content": {
            "application/json": {
              "schema": {
                "$ref": "#/components/schemas/FlightDetailsRequestDto"
              }
            },
            "text/json": {
              "schema": {
                "$ref": "#/components/schemas/FlightDetailsRequestDto"
              }
            },
            "application/*+json": {
              "schema": {
                "$ref": "#/components/schemas/FlightDetailsRequestDto"
              }
            }
          }
        },
        "responses": {
          "400": {
            "description": "Bad Request",
            "content": {
              "text/plain": {
                "schema": {
                  "$ref": "#/components/schemas/JsonResponse"
                }
              },
              "application/json": {
                "schema": {
                  "$ref": "#/components/schemas/JsonResponse"
                }
              },
              "text/json": {
                "schema": {
                  "$ref": "#/components/schemas/JsonResponse"
                }
              }
            }
          },
          "401": {
            "description": "Unauthorized",
            "content": {
              "text/plain": {
                "schema": {
                  "$ref": "#/components/schemas/JsonResponse"
                }
              },
              "application/json": {
                "schema": {
                  "$ref": "#/components/schemas/JsonResponse"
                }
              },
              "text/json": {
                "schema": {
                  "$ref": "#/components/schemas/JsonResponse"
                }
              }
            }
          },
          "500": {
            "description": "Internal Server Error",
            "content": {
              "text/plain": {
                "schema": {
                  "$ref": "#/components/schemas/JsonResponse"
                }
              },
              "application/json": {
                "schema": {
                  "$ref": "#/components/schemas/JsonResponse"
                }
              },
              "text/json": {
                "schema": {
                  "$ref": "#/components/schemas/JsonResponse"
                }
              }
            }
          },
          "default": {
            "description": "Unexpected error",
            "content": {
              "application/json": {
                "schema": {
                  "$ref": "#/components/schemas/JsonResponse"
                }
              }
            }
          }
        }
      }
    },
    "/Flight/PNRGenerate": {
      "post": {
        "tags": [
          "Flight"
        ],
        "requestBody": {
          "content": {
            "application/json": {
              "schema": {
                "$ref": "#/components/schemas/CreateFlightOrderDTO"
              }
            },
            "text/json": {
              "schema": {
                "$ref": "#/components/schemas/CreateFlightOrderDTO"
              }
            },
            "application/*+json": {
              "schema": {
                "$ref": "#/components/schemas/CreateFlightOrderDTO"
              }
            }
          }
        },
        "responses": {
          "400": {
            "description": "Bad Request",
            "content": {
              "text/plain": {
                "schema": {
                  "$ref": "#/components/schemas/JsonResponse"
                }
              },
              "application/json": {
                "schema": {
                  "$ref": "#/components/schemas/JsonResponse"
                }
              },
              "text/json": {
                "schema": {
                  "$ref": "#/components/schemas/JsonResponse"
                }
              }
            }
          },
          "401": {
            "description": "Unauthorized",
            "content": {
              "text/plain": {
                "schema": {
                  "$ref": "#/components/schemas/JsonResponse"
                }
              },
              "application/json": {
                "schema": {
                  "$ref": "#/components/schemas/JsonResponse"
                }
              },
              "text/json": {
                "schema": {
                  "$ref": "#/components/schemas/JsonResponse"
                }
              }
            }
          },
          "500": {
            "description": "Internal Server Error",
            "content": {
              "text/plain": {
                "schema": {
                  "$ref": "#/components/schemas/JsonResponse"
                }
              },
              "application/json": {
                "schema": {
                  "$ref": "#/components/schemas/JsonResponse"
                }
              },
              "text/json": {
                "schema": {
                  "$ref": "#/components/schemas/JsonResponse"
                }
              }
            }
          },
          "default": {
            "description": "Unexpected error",
            "content": {
              "application/json": {
                "schema": {
                  "$ref": "#/components/schemas/JsonResponse"
                }
              }
            }
          }
        }
      }
    },
    "/Payment/create-order": {
      "post": {
        "tags": [
          "Payment"
        ],
        "requestBody": {
          "content": {
            "application/json": {
              "schema": {
                "$ref": "#/components/schemas/AddPaymentDto"
              }
            },
            "text/json": {
              "schema": {
                "$ref": "#/components/schemas/AddPaymentDto"
              }
            },
            "application/*+json": {
              "schema": {
                "$ref": "#/components/schemas/AddPaymentDto"
              }
            }
          }
        },
        "responses": {
          "400": {
            "description": "Bad Request",
            "content": {
              "text/plain": {
                "schema": {
                  "$ref": "#/components/schemas/JsonResponse"
                }
              },
              "application/json": {
                "schema": {
                  "$ref": "#/components/schemas/JsonResponse"
                }
              },
              "text/json": {
                "schema": {
                  "$ref": "#/components/schemas/JsonResponse"
                }
              }
            }
          },
          "401": {
            "description": "Unauthorized",
            "content": {
              "text/plain": {
                "schema": {
                  "$ref": "#/components/schemas/JsonResponse"
                }
              },
              "application/json": {
                "schema": {
                  "$ref": "#/components/schemas/JsonResponse"
                }
              },
              "text/json": {
                "schema": {
                  "$ref": "#/components/schemas/JsonResponse"
                }
              }
            }
          },
          "500": {
            "description": "Internal Server Error",
            "content": {
              "text/plain": {
                "schema": {
                  "$ref": "#/components/schemas/JsonResponse"
                }
              },
              "application/json": {
                "schema": {
                  "$ref": "#/components/schemas/JsonResponse"
                }
              },
              "text/json": {
                "schema": {
                  "$ref": "#/components/schemas/JsonResponse"
                }
              }
            }
          },
          "default": {
            "description": "Unexpected error",
            "content": {
              "application/json": {
                "schema": {
                  "$ref": "#/components/schemas/JsonResponse"
                }
              }
            }
          }
        }
      }
    },
    "/Payment/verify": {
      "post": {
        "tags": [
          "Payment"
        ],
        "requestBody": {
          "content": {
            "application/json": {
              "schema": {
                "$ref": "#/components/schemas/VerifyPaymentDto"
              }
            },
            "text/json": {
              "schema": {
                "$ref": "#/components/schemas/VerifyPaymentDto"
              }
            },
            "application/*+json": {
              "schema": {
                "$ref": "#/components/schemas/VerifyPaymentDto"
              }
            }
          }
        },
        "responses": {
          "400": {
            "description": "Bad Request",
            "content": {
              "text/plain": {
                "schema": {
                  "$ref": "#/components/schemas/JsonResponse"
                }
              },
              "application/json": {
                "schema": {
                  "$ref": "#/components/schemas/JsonResponse"
                }
              },
              "text/json": {
                "schema": {
                  "$ref": "#/components/schemas/JsonResponse"
                }
              }
            }
          },
          "401": {
            "description": "Unauthorized",
            "content": {
              "text/plain": {
                "schema": {
                  "$ref": "#/components/schemas/JsonResponse"
                }
              },
              "application/json": {
                "schema": {
                  "$ref": "#/components/schemas/JsonResponse"
                }
              },
              "text/json": {
                "schema": {
                  "$ref": "#/components/schemas/JsonResponse"
                }
              }
            }
          },
          "500": {
            "description": "Internal Server Error",
            "content": {
              "text/plain": {
                "schema": {
                  "$ref": "#/components/schemas/JsonResponse"
                }
              },
              "application/json": {
                "schema": {
                  "$ref": "#/components/schemas/JsonResponse"
                }
              },
              "text/json": {
                "schema": {
                  "$ref": "#/components/schemas/JsonResponse"
                }
              }
            }
          },
          "default": {
            "description": "Unexpected error",
            "content": {
              "application/json": {
                "schema": {
                  "$ref": "#/components/schemas/JsonResponse"
                }
              }
            }
          }
        }
      }
    },
    "/Payment/webhook/{gatewayType}": {
      "post": {
        "tags": [
          "Payment"
        ],
        "parameters": [
          {
            "name": "gatewayType",
            "in": "path",
            "required": true,
            "schema": {
              "$ref": "#/components/schemas/PaymentGatewayType"
            }
          }
        ],
        "responses": {
          "400": {
            "description": "Bad Request",
            "content": {
              "text/plain": {
                "schema": {
                  "$ref": "#/components/schemas/JsonResponse"
                }
              },
              "application/json": {
                "schema": {
                  "$ref": "#/components/schemas/JsonResponse"
                }
              },
              "text/json": {
                "schema": {
                  "$ref": "#/components/schemas/JsonResponse"
                }
              }
            }
          },
          "401": {
            "description": "Unauthorized",
            "content": {
              "text/plain": {
                "schema": {
                  "$ref": "#/components/schemas/JsonResponse"
                }
              },
              "application/json": {
                "schema": {
                  "$ref": "#/components/schemas/JsonResponse"
                }
              },
              "text/json": {
                "schema": {
                  "$ref": "#/components/schemas/JsonResponse"
                }
              }
            }
          },
          "500": {
            "description": "Internal Server Error",
            "content": {
              "text/plain": {
                "schema": {
                  "$ref": "#/components/schemas/JsonResponse"
                }
              },
              "application/json": {
                "schema": {
                  "$ref": "#/components/schemas/JsonResponse"
                }
              },
              "text/json": {
                "schema": {
                  "$ref": "#/components/schemas/JsonResponse"
                }
              }
            }
          },
          "default": {
            "description": "Unexpected error",
            "content": {
              "application/json": {
                "schema": {
                  "$ref": "#/components/schemas/JsonResponse"
                }
              }
            }
          }
        }
      }
    }
  },
  "components": {
    "schemas": {
      "AddPaymentDto": {
        "type": "object",
        "properties": {
          "usrno": {
            "type": "integer",
            "format": "int32"
          },
          "amount": {
            "type": "number",
            "format": "double"
          },
          "gatewayType": {
            "$ref": "#/components/schemas/PaymentGatewayType"
          }
        },
        "additionalProperties": false
      },
      "CityAirportList": {
        "type": "object",
        "properties": {
          "airportId": {
            "type": "integer",
            "format": "int32"
          },
          "cityName": {
            "type": "string",
            "nullable": true
          },
          "airport": {
            "type": "string",
            "nullable": true
          },
          "iataCode": {
            "type": "string",
            "nullable": true
          },
          "icaoCode": {
            "type": "string",
            "nullable": true
          }
        },
        "additionalProperties": false
      },
      "CityAirportListListJsonResponse": {
        "type": "object",
        "properties": {
          "status": {
            "type": "integer",
            "format": "int32"
          },
          "message": {
            "type": "string",
            "nullable": true
          },
          "data": {
            "type": "array",
            "items": {
              "$ref": "#/components/schemas/CityAirportList"
            },
            "nullable": true
          }
        },
        "additionalProperties": false
      },
      "CreateFlightOrderDTO": {
        "type": "object",
        "properties": {
          "tripType": {
            "type": "string",
            "nullable": true
          },
          "cacheKey": {
            "type": "string",
            "nullable": true
          },
          "offerId": {
            "type": "string",
            "nullable": true
          },
          "countryCode": {
            "type": "string",
            "nullable": true
          },
          "mobile": {
            "type": "string",
            "nullable": true
          },
          "email": {
            "type": "string",
            "nullable": true
          },
          "state": {
            "type": "string",
            "nullable": true
          },
          "paymentMode": {
            "type": "string",
            "nullable": true
          },
          "adults": {
            "type": "array",
            "items": {
              "$ref": "#/components/schemas/PassangerDetail"
            },
            "nullable": true
          },
          "childs": {
            "type": "array",
            "items": {
              "$ref": "#/components/schemas/PassangerDetail"
            },
            "nullable": true
          },
          "infants": {
            "type": "array",
            "items": {
              "$ref": "#/components/schemas/PassangerDetail"
            },
            "nullable": true
          }
        },
        "additionalProperties": false
      },
      "Description": {
        "type": "object",
        "properties": {
          "descriptionType": {
            "type": "string",
            "nullable": true
          },
          "text": {
            "type": "string",
            "nullable": true
          }
        },
        "additionalProperties": false
      },
      "FareNotes": {
        "type": "object",
        "properties": {
          "descriptions": {
            "type": "array",
            "items": {
              "$ref": "#/components/schemas/Description"
            },
            "nullable": true
          }
        },
        "additionalProperties": false
      },
      "FareRule": {
        "type": "object",
        "properties": {
          "fareBasis": {
            "type": "string",
            "nullable": true
          },
          "name": {
            "type": "string",
            "nullable": true
          },
          "fareNotes": {
            "$ref": "#/components/schemas/FareNotes"
          }
        },
        "additionalProperties": false
      },
      "FlightDetailModel": {
        "type": "object",
        "properties": {
          "cacheKey": {
            "type": "string",
            "nullable": true
          },
          "tripType": {
            "type": "string",
            "nullable": true
          },
          "flightItineraries": {
            "type": "array",
            "items": {
              "$ref": "#/components/schemas/FlightItinerariesModel"
            },
            "nullable": true
          },
          "flightSummary": {
            "$ref": "#/components/schemas/FlightSummaryModel"
          }
        },
        "additionalProperties": false
      },
      "FlightDetailModelJsonResponse": {
        "type": "object",
        "properties": {
          "status": {
            "type": "integer",
            "format": "int32"
          },
          "message": {
            "type": "string",
            "nullable": true
          },
          "data": {
            "$ref": "#/components/schemas/FlightDetailModel"
          }
        },
        "additionalProperties": false
      },
      "FlightDetailsRequestDto": {
        "type": "object",
        "properties": {
          "cacheKey": {
            "type": "string",
            "nullable": true
          },
          "offerId": {
            "type": "string",
            "nullable": true
          },
          "tripType": {
            "type": "string",
            "nullable": true
          }
        },
        "additionalProperties": false
      },
      "FlightFilters": {
        "type": "object",
        "properties": {
          "filterKey": {
            "type": "string",
            "nullable": true
          },
          "title": {
            "type": "string",
            "nullable": true
          },
          "type": {
            "type": "string",
            "nullable": true
          },
          "items": {
            "nullable": true
          }
        },
        "additionalProperties": false
      },
      "FlightItinerariesModel": {
        "type": "object",
        "properties": {
          "offerId": {
            "type": "string",
            "nullable": true
          },
          "fromCity": {
            "type": "string",
            "nullable": true
          },
          "toCity": {
            "type": "string",
            "nullable": true
          },
          "travelDate": {
            "type": "string",
            "nullable": true
          },
          "stops": {
            "type": "integer",
            "format": "int32"
          },
          "duration": {
            "type": "string",
            "nullable": true
          },
          "segments": {
            "type": "array",
            "items": {
              "$ref": "#/components/schemas/SegmentDetail"
            },
            "nullable": true
          }
        },
        "additionalProperties": false
      },
      "FlightItinerary": {
        "type": "object",
        "properties": {
          "fromCity": {
            "type": "string",
            "nullable": true
          },
          "toCity": {
            "type": "string",
            "nullable": true
          },
          "fromIata": {
            "type": "string",
            "nullable": true
          },
          "toIata": {
            "type": "string",
            "nullable": true
          },
          "departureDate": {
            "type": "string",
            "format": "date-time"
          },
          "departureTime": {
            "type": "string",
            "nullable": true
          },
          "arrivalDate": {
            "type": "string",
            "format": "date-time"
          },
          "arrivalTime": {
            "type": "string",
            "nullable": true
          },
          "airlineLogo": {
            "type": "string",
            "nullable": true
          },
          "airlineName": {
            "type": "string",
            "nullable": true
          },
          "airlineCode": {
            "type": "string",
            "nullable": true
          },
          "flightNumber": {
            "type": "string",
            "nullable": true
          },
          "duration": {
            "type": "string",
            "nullable": true
          },
          "aircraftCode": {
            "type": "string",
            "nullable": true
          },
          "aircraftName": {
            "type": "string",
            "nullable": true
          },
          "stops": {
            "type": "integer",
            "format": "int32"
          },
          "via": {
            "type": "string",
            "nullable": true
          },
          "price": {
            "type": "string",
            "nullable": true
          }
        },
        "additionalProperties": false
      },
      "FlightResults": {
        "type": "object",
        "properties": {
          "supplier": {
            "type": "string",
            "nullable": true
          },
          "cacheKey": {
            "type": "string",
            "nullable": true
          },
          "search": {
            "$ref": "#/components/schemas/SearchRequestDto"
          },
          "data": {
            "type": "array",
            "items": {
              "$ref": "#/components/schemas/OfferData"
            },
            "nullable": true
          },
          "filters": {
            "type": "array",
            "items": {
              "$ref": "#/components/schemas/FlightFilters"
            },
            "nullable": true
          }
        },
        "additionalProperties": false
      },
      "FlightResultsJsonResponse": {
        "type": "object",
        "properties": {
          "status": {
            "type": "integer",
            "format": "int32"
          },
          "message": {
            "type": "string",
            "nullable": true
          },
          "data": {
            "$ref": "#/components/schemas/FlightResults"
          }
        },
        "additionalProperties": false
      },
      "FlightSummaryModel": {
        "type": "object",
        "properties": {
          "baseFare": {
            "type": "number",
            "format": "double"
          },
          "adult": {
            "type": "integer",
            "format": "int32"
          },
          "adultBasePrice": {
            "type": "number",
            "format": "double"
          },
          "adultTotalPrice": {
            "type": "number",
            "format": "double"
          },
          "children": {
            "type": "integer",
            "format": "int32"
          },
          "childrenBasePrice": {
            "type": "number",
            "format": "double"
          },
          "childrenTotalPrice": {
            "type": "number",
            "format": "double"
          },
          "infant": {
            "type": "integer",
            "format": "int32"
          },
          "infantBasePrice": {
            "type": "number",
            "format": "double"
          },
          "infantTotalPrice": {
            "type": "number",
            "format": "double"
          },
          "taxesServiceCharges": {
            "type": "number",
            "format": "double"
          },
          "totalPrice": {
            "type": "number",
            "format": "double"
          },
          "universalMarkup": {
            "type": "number",
            "format": "double"
          },
          "airlineMarkup": {
            "type": "number",
            "format": "double"
          }
        },
        "additionalProperties": false
      },
      "GetByUsrno": {
        "type": "object",
        "properties": {
          "usrno": {
            "type": "integer",
            "format": "int32"
          }
        },
        "additionalProperties": false
      },
      "IncludedBags": {
        "type": "object",
        "properties": {
          "weight": {
            "type": "string",
            "nullable": true
          },
          "weightUnit": {
            "type": "string",
            "nullable": true
          }
        },
        "additionalProperties": false
      },
      "JsonResponse": {
        "type": "object",
        "properties": {
          "status": {
            "type": "integer",
            "format": "int32"
          },
          "message": {
            "type": "string",
            "nullable": true
          },
          "data": {
            "nullable": true
          }
        },
        "additionalProperties": false
      },
      "LoginDto": {
        "type": "object",
        "properties": {
          "userId": {
            "type": "string",
            "nullable": true
          },
          "password": {
            "type": "string",
            "nullable": true
          },
          "userType": {
            "type": "string",
            "nullable": true
          }
        },
        "additionalProperties": false
      },
      "LoginViaOtpModel": {
        "type": "object",
        "properties": {
          "mobile": {
            "type": "string",
            "nullable": true
          }
        },
        "additionalProperties": false
      },
      "OfferData": {
        "type": "object",
        "properties": {
          "offerId": {
            "type": "string",
            "nullable": true
          },
          "itineraries": {
            "type": "array",
            "items": {
              "$ref": "#/components/schemas/FlightItinerary"
            },
            "nullable": true
          }
        },
        "additionalProperties": false
      },
      "OriginDestination": {
        "required": [
          "depatureDate",
          "fromCity",
          "toCity"
        ],
        "type": "object",
        "properties": {
          "fromCity": {
            "minLength": 1,
            "type": "string"
          },
          "toCity": {
            "minLength": 1,
            "type": "string"
          },
          "depatureDate": {
            "minLength": 1,
            "type": "string"
          }
        },
        "additionalProperties": false
      },
      "PassangerDetail": {
        "type": "object",
        "properties": {
          "firstName": {
            "type": "string",
            "nullable": true
          },
          "lastName": {
            "type": "string",
            "nullable": true
          },
          "gender": {
            "type": "string",
            "nullable": true
          },
          "countryCode": {
            "type": "string",
            "nullable": true
          },
          "mobile": {
            "type": "string",
            "nullable": true
          },
          "email": {
            "type": "string",
            "nullable": true
          },
          "frequentFlyerAirline": {
            "type": "string",
            "nullable": true
          },
          "frequentFlyerNo": {
            "type": "string",
            "nullable": true
          },
          "dob": {
            "type": "string",
            "nullable": true
          },
          "isRequiredWheelChair": {
            "type": "boolean",
            "nullable": true
          },
          "isHasFrequentFlyerNumber": {
            "type": "boolean",
            "nullable": true
          }
        },
        "additionalProperties": false
      },
      "PaymentGatewayType": {
        "enum": [
          1,
          2,
          3
        ],
        "type": "integer",
        "format": "int32"
      },
      "SearchAirport": {
        "type": "object",
        "properties": {
          "keyword": {
            "type": "string",
            "nullable": true
          }
        },
        "additionalProperties": false
      },
      "SearchRequestDto": {
        "required": [
          "cabinClass",
          "currencyCode",
          "destinations",
          "tripType"
        ],
        "type": "object",
        "properties": {
          "tripType": {
            "minLength": 1,
            "type": "string"
          },
          "currencyCode": {
            "minLength": 1,
            "type": "string"
          },
          "destinations": {
            "type": "array",
            "items": {
              "$ref": "#/components/schemas/OriginDestination"
            }
          },
          "returnDate": {
            "type": "string",
            "nullable": true
          },
          "cabinClass": {
            "minLength": 1,
            "type": "string"
          },
          "adults": {
            "type": "integer",
            "format": "int32"
          },
          "children": {
            "type": "integer",
            "format": "int32"
          },
          "infant": {
            "type": "integer",
            "format": "int32"
          },
          "maxResult": {
            "type": "integer",
            "format": "int32"
          }
        },
        "additionalProperties": false
      },
      "SegmentDetail": {
        "type": "object",
        "properties": {
          "segmentId": {
            "type": "integer",
            "format": "int32"
          },
          "airlineName": {
            "type": "string",
            "nullable": true
          },
          "airlineLogo": {
            "type": "string",
            "nullable": true
          },
          "airlineCode": {
            "type": "string",
            "nullable": true
          },
          "airCraftCode": {
            "type": "string",
            "nullable": true
          },
          "cabinClass": {
            "type": "string",
            "nullable": true
          },
          "cabinClassType": {
            "type": "string",
            "nullable": true
          },
          "fromCity": {
            "type": "string",
            "nullable": true
          },
          "fromAirport": {
            "type": "string",
            "nullable": true
          },
          "toCity": {
            "type": "string",
            "nullable": true
          },
          "toAirport": {
            "type": "string",
            "nullable": true
          },
          "depatureTime": {
            "type": "string",
            "nullable": true
          },
          "arrivalTime": {
            "type": "string",
            "nullable": true
          },
          "departureTerminal": {
            "type": "string",
            "nullable": true
          },
          "arrivalTerminal": {
            "type": "string",
            "nullable": true
          },
          "flightNumber": {
            "type": "string",
            "nullable": true
          },
          "duration": {
            "type": "string",
            "nullable": true
          },
          "cabinBaggage": {
            "$ref": "#/components/schemas/IncludedBags"
          },
          "checkInBaggage": {
            "$ref": "#/components/schemas/IncludedBags"
          },
          "fareRule": {
            "$ref": "#/components/schemas/FareRule"
          },
          "isExtraBaggage": {
            "type": "integer",
            "format": "int32"
          },
          "baggageQuantity": {
            "type": "integer",
            "format": "int32"
          },
          "baggagePrice": {
            "type": "string",
            "nullable": true
          }
        },
        "additionalProperties": false
      },
      "VerifyPaymentDto": {
        "type": "object",
        "properties": {
          "orderId": {
            "type": "string",
            "nullable": true
          },
          "paymentId": {
            "type": "string",
            "nullable": true
          },
          "signature": {
            "type": "string",
            "nullable": true
          },
          "gatewayType": {
            "$ref": "#/components/schemas/PaymentGatewayType"
          }
        },
        "additionalProperties": false
      }
    },
    "securitySchemes": {
      "Bearer": {
        "type": "http",
        "description": "Enter token like: Bearer {your token}",
        "scheme": "Bearer",
        "bearerFormat": "JWT"
      }
    }
  },
  "security": [
    {
      "Bearer": [ ]
    }
  ]
}